feed_processor/__init__.py
feed_processor/data_filter.py
feed_processor-0.0.1.dist-info/METADATA
feed_processor-0.0.1.dist-info/WHEEL
feed_processor-0.0.1.dist-info/licenses/LICENSE
feed_processor-0.0.1.dist-info/RECORD
